[
  {
    "author": "Andreas Pardeike",
    "name": "Harmony",
    "steamId": "2009463077",
    "version": "2.4.2.0"
  },
  {
    "author": "UnlimitedHugs",
    "name": "HugsLib",
    "steamId": "3513789221",
    "version": "11.0.5"
  },
  {
    "author": "nry",
    "name": "ToolkitCore",
    "steamId": "3013877477",
    "version": "1.0.0+7d0a90f98cb48c28759783d7c0a07f9c70b8ba21"
  },
  {
    "author": "nry",
    "name": "Twitch Toolkit",
    "steamId": "3013874066",
    "version": "2.0.10.0"
  },
  {
    "author": "swemoney",
    "name": "Toolkit - Channel Points",
    "steamId": "1916651243",
    "version": "1.6.0"
  },
  {
    "author": "SirRandoo",
    "name": "ToolkitUtils",
    "steamId": "2009500580",
    "version": "7.0.6.0-RC1+1ca7c6f6287e48f5f245b4c8dee252be6f2eda94"
  },
  {
    "author": "RimWorld-CrowdControl",
    "name": "RimWorld CrowdControl",
    "steamId": null,
    "version": null
  }
]
